README.rst
setup.py
src/yapsc.py
src/yapsc.egg-info/PKG-INFO
src/yapsc.egg-info/SOURCES.txt
src/yapsc.egg-info/dependency_links.txt
src/yapsc.egg-info/not-zip-safe
src/yapsc.egg-info/top_level.txt
test/test_yapsc.py