Metadata-Version: 1.2
Name: yapsc
Version: 0.1.4
Summary: Yet Another Python Switch-Case
Home-page: https://github.com/abarker/yapsc
Author: Allen Barker
Author-email: Allen.L.Barker@gmail.com
License: MIT
Keywords: switch,case,metaprogramming
Platform: UNKNOWN
Classifier: Development Status :: 4 - Beta
Classifier: Intended Audience :: Developers
Classifier: License :: OSI Approved :: MIT License
Classifier: Operating System :: Unix
Classifier: Operating System :: POSIX
Classifier: Operating System :: Microsoft :: Windows
Classifier: Programming Language :: Python
Classifier: Programming Language :: Python :: 3
Classifier: Programming Language :: Python :: Implementation :: CPython
Classifier: Programming Language :: Python :: Implementation :: PyPy
Classifier: Topic :: Utilities
Requires-Python: >=3.4
